topsis/__init__.py
topsis/topsis.py
Topsis_Prabhjot_102203767-1.0.2.dist-info/LICENSE
Topsis_Prabhjot_102203767-1.0.2.dist-info/METADATA
Topsis_Prabhjot_102203767-1.0.2.dist-info/WHEEL
Topsis_Prabhjot_102203767-1.0.2.dist-info/entry_points.txt
Topsis_Prabhjot_102203767-1.0.2.dist-info/top_level.txt
Topsis_Prabhjot_102203767-1.0.2.dist-info/RECORD
