Metadata-Version: 2.2
Name: Topsis_Prabhjot_102203767
Version: 1.0.2
Summary: A Python package to perform TOPSIS (Technique for Order Preference by Similarity to Ideal Solution)
Home-page: https://github.com/prabhjotk1306/Topsis
Author: Prabhjot
Author-email: prabhjotkaurchh@gmail.com
Classifier: Programming Language :: Python :: 3
Classifier: License :: OSI Approved :: MIT License
Classifier: Operating System :: OS Independent
Requires-Python: >=3.6
License-File: LICENSE
Requires-Dist: numpy
Requires-Dist: pandas
Dynamic: author
Dynamic: author-email
Dynamic: classifier
Dynamic: description
Dynamic: description-content-type
Dynamic: home-page
Dynamic: requires-dist
Dynamic: requires-python
Dynamic: summary
